README.md
setup.py
bin/git-hook
bin/literate-git-hooks
literacy/__init__.py
literacy/clean.py
literacy.egg-info/PKG-INFO
literacy.egg-info/SOURCES.txt
literacy.egg-info/dependency_links.txt
literacy.egg-info/not-zip-safe
literacy.egg-info/top_level.txt