Metadata-Version: 2.1
Name: literacy
Version: 0.2.1
Summary: Tools for literate programming in python and jupyter notebooks, following the functionality of Fastai v2 dev https://github.com/fastai/fastai_dev
Home-page: https://github.com/holyfiddlex/literacy
Author: Héctor de la Rosa Prado
Author-email: hoftherose@gmail.com
License: MIT
Platform: UNKNOWN
